.gitignore
CONTRIBUTING.md
LICENSE
README.md
setup.py
.github/ISSUE_TEMPLATE/bug_report.md
.github/ISSUE_TEMPLATE/feature_request.md
examples/plotroutines.py
examples/ExactCover/ExactCover 6 3.ipynb
examples/ExactCover/tailassignment_loader.py
examples/ExactCover/data/FRCR_6_24_3.txt
examples/MaxCut/CVaR.ipynb
examples/MaxCut/ComparisonOptimizers.ipynb
examples/MaxCut/ComparisonPostProcessing.ipynb
examples/MaxCut/ConstrainedCase.ipynb
examples/MaxCut/ToyExample.ipynb
examples/MaxCut/WithFlip.ipynb
examples/MaxCut/data/w_ba_n10_k4_0.gml
examples/MaxCut/data/w_ba_n21_k4_0.gml
examples/PortfolioOptimization/PortOpt.ipynb
examples/PortfolioOptimization/asset_loader.py
examples/PortfolioOptimization/data/qiskit_finance_seeds.npz
images/E.png
maxkcut/__init__.py
qaoa/__init__.py
qaoa/qaoa.py
qaoa.egg-info/PKG-INFO
qaoa.egg-info/SOURCES.txt
qaoa.egg-info/dependency_links.txt
qaoa.egg-info/requires.txt
qaoa.egg-info/top_level.txt
qaoa/initialstates/__init__.py
qaoa/initialstates/base_initialstate.py
qaoa/initialstates/dicke1_2_initialstate.py
qaoa/initialstates/dicke_initialstate.py
qaoa/initialstates/lessthank_initialstate.py
qaoa/initialstates/maxkcut_feasible_initialstate.py
qaoa/initialstates/plus_initialstate.py
qaoa/initialstates/statevector_initialstate.py
qaoa/initialstates/tensor_initialstate.py
qaoa/mixers/__init__.py
qaoa/mixers/base_mixer.py
qaoa/mixers/grover_mixer.py
qaoa/mixers/maxkcut_grover_mixer.py
qaoa/mixers/maxkcut_lx_mixer.py
qaoa/mixers/x_mixer.py
qaoa/mixers/xy_mixer.py
qaoa/mixers/xy_tensor.py
qaoa/problems/__init__.py
qaoa/problems/base_problem.py
qaoa/problems/exactcover_problem.py
qaoa/problems/graph_problem.py
qaoa/problems/maxkcut_binary_fullH.py
qaoa/problems/maxkcut_binary_powertwo.py
qaoa/problems/maxkcut_one_hot_problem.py
qaoa/problems/portfolio_problem.py
qaoa/problems/qubo_problem.py
qaoa/util/__init__.py
qaoa/util/flip.py
qaoa/util/graphutils.py
qaoa/util/post.py
qaoa/util/statistic.py
unittests/__init__.py
unittests/test_maxkcut_binary_problem.py
unittests/test_maxkcut_feasible_initialstate.py
unittests/test_maxkcut_mixers.py
unittests/test_maxkcut_one_hot_problem.py