Metadata-Version: 2.1
Name: qaoa
Version: 1.2.1
Summary: Quantum Alternating Operator Ansatz/Quantum Approximate Optimization Algorithm (QAOA)
Author: Franz Georg Fuchs
Author-email: franzgeorgfuchs@gmail.com
License: GNU General Public License v3.0
Keywords: quantum computing,qaoa,qiskit
License-File: LICENSE
Requires-Dist: numpy
Requires-Dist: scipy
Requires-Dist: structlog
Requires-Dist: matplotlib
Requires-Dist: networkx
Requires-Dist: jupyter
Requires-Dist: qiskit==1.1.1
Requires-Dist: qiskit-aer
Requires-Dist: qiskit-algorithms
Requires-Dist: qiskit-finance
Requires-Dist: pylatexenc
